igeGamesServices.cp39-win_amd64.pyd
igeGamesServices-0.1.1.dist-info/LICENSE
igeGamesServices-0.1.1.dist-info/METADATA
igeGamesServices-0.1.1.dist-info/WHEEL
igeGamesServices-0.1.1.dist-info/top_level.txt
igeGamesServices-0.1.1.dist-info/RECORD
